[
  {
    "artist": [
      "Christkindlmarket"
    ],
    "link": "https://dice.fm/event/69274b04b4856100015a74e8",
    "date": "2025-12-13T11:00:00-05:00",
    "venue": "Mahall\u2019s"
  },
  {
    "artist": [
      "Rivers of Nihil"
    ],
    "link": "https://dice.fm/event/68b07f40c159860001a22d45",
    "date": "2025-12-13T19:00:00-05:00",
    "venue": "Mahall\u2019s"
  },
  {
    "artist": [
      "Christkindlmarket"
    ],
    "link": "https://dice.fm/event/69389e33e17d9a00013a5a1d",
    "date": "2025-12-14T11:00:00-05:00",
    "venue": "Mahall\u2019s"
  },
  {
    "artist": [
      "Young Culture"
    ],
    "link": "https://dice.fm/event/6887842cdaa2ef000190bf26",
    "date": "2025-12-14T19:00:00-05:00",
    "venue": "Mahall\u2019s"
  },
  {
    "artist": [
      "Samsara"
    ],
    "link": "https://dice.fm/event/690fd84e9fdcce0001edc93c",
    "date": "2025-12-17T19:00:00-05:00",
    "venue": "Mahall\u2019s"
  },
  {
    "artist": [
      "Moon Cactus"
    ],
    "link": "https://dice.fm/event/690fd8dcc90c4b00017fb6fb",
    "date": "2025-12-18T19:00:00-05:00",
    "venue": "Mahall\u2019s"
  },
  {
    "artist": [
      "TRUSS and Elbow Room"
    ],
    "link": "https://dice.fm/event/68f00953036e2500011e26d9",
    "date": "2025-12-19T18:00:00-05:00",
    "venue": "Mahall\u2019s"
  },
  {
    "artist": [
      "People in the Daytime"
    ],
    "link": "https://dice.fm/event/691a399a2d3b0600012e9959",
    "date": "2025-12-20T19:00:00-05:00",
    "venue": "Mahall\u2019s"
  },
  {
    "artist": [
      "Dead Bundy"
    ],
    "link": "https://dice.fm/event/68ee4c047b1fa60001a55fc0",
    "date": "2025-12-21T18:00:00-05:00",
    "venue": "Mahall\u2019s"
  },
  {
    "artist": [
      "Kid Primitive"
    ],
    "link": "https://dice.fm/event/691e54bd2a4bd4000146d537",
    "date": "2025-12-23T19:00:00-05:00",
    "venue": "Mahall\u2019s"
  },
  {
    "artist": [
      "Hammy New Year 3: The 3 Peat"
    ],
    "link": "https://dice.fm/event/68e95db4605c2000010dcb2d",
    "date": "2025-12-27T16:00:00-05:00",
    "venue": "The Roxy at Mahall\u2019s"
  },
  {
    "artist": [
      "Mahall's Mystery Movie and Trivia night"
    ],
    "link": "https://dice.fm/event/693b25ba4ce63100013c219c",
    "date": "2025-12-28T18:00:00-05:00",
    "venue": "Mahall\u2019s"
  },
  {
    "artist": [
      "Zombie Fashion Show"
    ],
    "link": "https://dice.fm/event/690fda6f5572650001c0cb10",
    "date": "2025-12-30T18:00:00-05:00",
    "venue": "Mahall\u2019s"
  },
  {
    "artist": [
      "Mahall's New Year's Eve party: Murder on the Dance Floor"
    ],
    "link": "https://dice.fm/event/6930baa6bd8faa0001e6cf9f",
    "date": "2025-12-31T20:00:00-05:00",
    "venue": "The Roxy at Mahall\u2019s"
  },
  {
    "artist": [
      "Gimme Gimme Disco"
    ],
    "link": "https://dice.fm/event/690e061728065a0001a3bff3",
    "date": "2026-01-03T21:00:00-05:00",
    "venue": "Mahall\u2019s"
  },
  {
    "artist": [
      "The Little Ditties"
    ],
    "link": "https://dice.fm/event/692dae544510540001cd85e1",
    "date": "2026-01-07T19:00:00-05:00",
    "venue": "Mahall\u2019s"
  },
  {
    "artist": [
      "Spill"
    ],
    "link": "https://dice.fm/event/692daebc6ca7e100016f9feb",
    "date": "2026-01-08T19:00:00-05:00",
    "venue": "Mahall\u2019s"
  },
  {
    "artist": [
      "Youth Fountain (acoustic)"
    ],
    "link": "https://dice.fm/event/68c42fc486b0cd000166e5d1",
    "date": "2026-01-11T19:00:00-05:00",
    "venue": "Mahall\u2019s"
  },
  {
    "artist": [
      "54 Ultra"
    ],
    "link": "https://dice.fm/event/68f0067b387090000137a05a",
    "date": "2026-01-14T19:00:00-05:00",
    "venue": "Mahall\u2019s"
  },
  {
    "artist": [
      "Breathe In Stereo"
    ],
    "link": "https://dice.fm/event/693b2ea307d6f40001ba3632",
    "date": "2026-01-16T18:30:00-05:00",
    "venue": "Mahall\u2019s"
  },
  {
    "artist": [
      "Pinkertones"
    ],
    "link": "https://dice.fm/event/68dbe6096c20da0001c8cda7",
    "date": "2026-01-17T19:00:00-05:00",
    "venue": "Mahall\u2019s"
  },
  {
    "artist": [
      "*VENUE UPGRADE* Racing Mount Pleasant"
    ],
    "link": "https://dice.fm/event/68fa5590778dc30001a07863",
    "date": "2026-01-18T19:00:00-05:00",
    "venue": "Mahall\u2019s"
  },
  {
    "artist": [
      "Buffchick and Ezra Glatt "
    ],
    "link": "https://dice.fm/event/691c8f9ae6cc21000100e259",
    "date": "2026-01-24T18:00:00-05:00",
    "venue": "Mahall\u2019s"
  },
  {
    "artist": [
      "Bad Bad Hats"
    ],
    "link": "https://dice.fm/event/68fb93d12b73fa000102a42a",
    "date": "2026-01-25T18:00:00-05:00",
    "venue": "Mahall\u2019s"
  },
  {
    "artist": [
      "Magic City Hippies"
    ],
    "link": "https://dice.fm/event/68dfe535fb741b0001e634d2",
    "date": "2026-01-28T19:00:00-05:00",
    "venue": "Mahall\u2019s"
  },
  {
    "artist": [
      "Bloomer"
    ],
    "link": "https://dice.fm/event/68daee2f20042a0001c658d3",
    "date": "2026-01-29T18:00:00-05:00",
    "venue": "Mahall\u2019s"
  },
  {
    "artist": [
      "Agriculture"
    ],
    "link": "https://dice.fm/event/68ded7a5a3667d0001200544",
    "date": "2026-02-07T19:00:00-05:00",
    "venue": "Mahall\u2019s"
  },
  {
    "artist": [
      "The Browning"
    ],
    "link": "https://dice.fm/event/690a76f705c376000157fd55",
    "date": "2026-02-13T18:00:00-05:00",
    "venue": "The Roxy at Mahall\u2019s"
  },
  {
    "artist": [
      "Dinosaur Pile-Up"
    ],
    "link": "https://dice.fm/event/691cdf12e6cc2100013bbae0",
    "date": "2026-02-15T19:00:00-05:00",
    "venue": "Mahall\u2019s"
  },
  {
    "artist": [
      "Good Terms"
    ],
    "link": "https://dice.fm/event/690a7b0e43748b0001741117",
    "date": "2026-02-25T18:00:00-05:00",
    "venue": "Mahall\u2019s"
  },
  {
    "artist": [
      "Mat Kerekes"
    ],
    "link": "https://dice.fm/event/68e6780e7051c80001abaad0",
    "date": "2026-03-05T19:00:00-05:00",
    "venue": "Mahall\u2019s"
  },
  {
    "artist": [
      "Worry Club: I'm Freaking Out Tour"
    ],
    "link": "https://dice.fm/event/6938a03923f0df0001f7d609",
    "date": "2026-03-06T18:00:00-05:00",
    "venue": "Mahall\u2019s"
  },
  {
    "artist": [
      "Capstan: Cultural Divide 10 Year Anniversary Tour"
    ],
    "link": "https://dice.fm/event/69111ad7c90c4b0001658f58",
    "date": "2026-03-10T18:00:00-04:00",
    "venue": "Mahall\u2019s"
  },
  {
    "artist": [
      "Coma Cinema and Trace Mountains"
    ],
    "link": "https://dice.fm/event/691b6a3a865aad0001d12ee8",
    "date": "2026-03-13T18:00:00-04:00",
    "venue": "Mahall\u2019s"
  },
  {
    "artist": [
      "ALEXSUCKS"
    ],
    "link": "https://dice.fm/event/69370830b3ec09000174c691",
    "date": "2026-03-14T18:00:00-04:00",
    "venue": "Mahall\u2019s"
  },
  {
    "artist": [
      "Sweet Pill"
    ],
    "link": "https://dice.fm/event/6912198e5a00bd00016ed83d",
    "date": "2026-03-14T19:00:00-04:00",
    "venue": "The Roxy at Mahall\u2019s"
  },
  {
    "artist": [
      "Ben Quad: Wisher Album Release Tour"
    ],
    "link": "https://dice.fm/event/692470b615ed660001fc1acf",
    "date": "2026-03-18T18:00:00-04:00",
    "venue": "Mahall\u2019s"
  },
  {
    "artist": [
      "Quarters"
    ],
    "link": "https://dice.fm/event/690baa8adeb4f800019d0b73",
    "date": "2026-03-19T18:00:00-04:00",
    "venue": "Mahall\u2019s"
  },
  {
    "artist": [
      "Twen"
    ],
    "link": "https://dice.fm/event/68d196cb32146f0001eec67d",
    "date": "2026-03-28T18:00:00-04:00",
    "venue": "Mahall\u2019s"
  },
  {
    "artist": [
      "Drain"
    ],
    "link": "https://dice.fm/event/690bbcd1ff2bad000182793b",
    "date": "2026-04-01T18:00:00-04:00",
    "venue": "The Roxy at Mahall\u2019s"
  },
  {
    "artist": [
      "Steinza"
    ],
    "link": "https://dice.fm/event/6924ab21f9076a00010ea85f",
    "date": "2026-04-03T19:00:00-04:00",
    "venue": "Mahall\u2019s"
  },
  {
    "artist": [
      "Bleed From Within"
    ],
    "link": "https://dice.fm/event/691b3517324bfa00011c95b8",
    "date": "2026-04-07T18:00:00-04:00",
    "venue": "The Roxy at Mahall\u2019s"
  },
  {
    "artist": [
      "Wallice"
    ],
    "link": "https://dice.fm/event/693087a9b73b370001b4d4b5",
    "date": "2026-04-10T19:00:00-04:00",
    "venue": "Mahall\u2019s"
  },
  {
    "artist": [
      "Carly Cosgrove"
    ],
    "link": "https://dice.fm/event/69323f3eec26850001bc9157",
    "date": "2026-04-12T18:30:00-04:00",
    "venue": "Mahall\u2019s"
  },
  {
    "artist": [
      "76th Street"
    ],
    "link": "https://dice.fm/event/690e0940dbcc030001f0f48e",
    "date": "2026-04-13T19:00:00-04:00",
    "venue": "Mahall\u2019s"
  },
  {
    "artist": [
      "Fantastic Negrito"
    ],
    "link": "https://dice.fm/event/68f68c3b252ed20001ecf082",
    "date": "2026-04-18T19:00:00-04:00",
    "venue": "Mahall\u2019s"
  },
  {
    "artist": [
      "Field Medic"
    ],
    "link": "https://dice.fm/event/69209b8af7015800017070e1",
    "date": "2026-04-23T19:00:00-04:00",
    "venue": "Mahall\u2019s"
  },
  {
    "artist": [
      "Vana: The Lady In Red Tour"
    ],
    "link": "https://dice.fm/event/691e7e09f53dd0000134c424",
    "date": "2026-04-29T18:00:00-04:00",
    "venue": "Mahall\u2019s"
  },
  {
    "artist": [
      "Melrose Avenue"
    ],
    "link": "https://dice.fm/event/68dda232855fc3000131b562",
    "date": "2026-04-30T19:00:00-04:00",
    "venue": "The Roxy at Mahall\u2019s"
  },
  {
    "artist": [
      "Fireworks"
    ],
    "link": "https://dice.fm/event/690bcbdfc5e79d00011afd8b",
    "date": "2026-05-11T19:00:00-04:00",
    "venue": "Mahall\u2019s"
  }
]
