[
  {
    "artist": [
      "Young the Giant, Cold War Kids, almost monday"
    ],
    "link": "https://www.jacobspavilion.com/events/detail?event_id=1324940",
    "date": "2026-05-27T00:00:01",
    "venue": "Jacobs Pavilion at Nautica"
  },
  {
    "artist": [
      "Russell Dickerson, Niko Moon, Adrien Nunez"
    ],
    "link": "https://www.jacobspavilion.com/events/detail?event_id=1121366",
    "date": "2026-05-29T00:00:01",
    "venue": "Jacobs Pavilion at Nautica"
  },
  {
    "artist": [
      "Claypool Gold, featuring Primus, Les Claypool's Frog Brigade, & The Claypool Lennon Delirium"
    ],
    "link": "https://www.jacobspavilion.com/events/detail?event_id=1294390",
    "date": "2026-06-02T00:00:01",
    "venue": "Jacobs Pavilion at Nautica"
  },
  {
    "artist": [
      "Hot Mulligan, Joyce Manor, Saturdays at Your Place, KOYO"
    ],
    "link": "https://www.jacobspavilion.com/events/detail?event_id=1300349",
    "date": "2026-06-04T00:00:01",
    "venue": "Jacobs Pavilion at Nautica"
  },
  {
    "artist": [
      "Mt. Joy"
    ],
    "link": "https://www.jacobspavilion.com/events/detail?event_id=1241396",
    "date": "2026-06-05T00:00:01",
    "venue": "Jacobs Pavilion at Nautica"
  },
  {
    "artist": [
      "The Avett Brothers & Mike Patton present AVTT/PTTN"
    ],
    "link": "https://www.jacobspavilion.com/events/detail?event_id=1225285",
    "date": "2026-06-18T00:00:01",
    "venue": "Jacobs Pavilion at Nautica"
  },
  {
    "artist": [
      "Death Cab for Cutie, Jay Som"
    ],
    "link": "https://www.jacobspavilion.com/events/detail?event_id=1298166",
    "date": "2026-07-15T00:00:01",
    "venue": "Jacobs Pavilion at Nautica"
  },
  {
    "artist": [
      "Louis Tomlinson, The Beaches"
    ],
    "link": "https://www.jacobspavilion.com/events/detail?event_id=1158181",
    "date": "2026-07-20T00:00:01",
    "venue": "Jacobs Pavilion at Nautica"
  },
  {
    "artist": [
      "Slightly Stoopid, THE ELOVATERS, Bumpin Uglies"
    ],
    "link": "https://www.jacobspavilion.com/events/detail?event_id=1353095",
    "date": "2026-07-23T00:00:01",
    "venue": "Jacobs Pavilion at Nautica"
  },
  {
    "artist": [
      "Zeds Dead"
    ],
    "link": "https://www.jacobspavilion.com/events/detail?event_id=1335872",
    "date": "2026-07-24T00:00:01",
    "venue": "Jacobs Pavilion at Nautica"
  },
  {
    "artist": [
      "Brit Floyd"
    ],
    "link": "https://www.jacobspavilion.com/events/detail?event_id=1312904",
    "date": "2026-07-26T00:00:01",
    "venue": "Jacobs Pavilion at Nautica"
  },
  {
    "artist": [
      "The Fray, Dashboard Confessional and Colony House"
    ],
    "link": "https://www.jacobspavilion.com/events/detail?event_id=1307132",
    "date": "2026-08-12T00:00:01",
    "venue": "Jacobs Pavilion at Nautica"
  },
  {
    "artist": [
      "Simple Plan, 3OH!3, Bowling For Soup"
    ],
    "link": "https://www.jacobspavilion.com/events/detail?event_id=1326879",
    "date": "2026-08-13T00:00:01",
    "venue": "Jacobs Pavilion at Nautica"
  },
  {
    "artist": [
      "Ella Mai, AMA and Girlfriend"
    ],
    "link": "https://www.jacobspavilion.com/events/detail?event_id=1365876",
    "date": "2026-08-22T00:00:01",
    "venue": "Jacobs Pavilion at Nautica"
  },
  {
    "artist": [
      "NEEDTOBREATHE, Drew Holcomb & Ellie Holcomb"
    ],
    "link": "https://www.jacobspavilion.com/events/detail?event_id=1362163",
    "date": "2026-08-28T00:00:01",
    "venue": "Jacobs Pavilion at Nautica"
  },
  {
    "artist": [
      "Gavin Adcock, Jake Worthington and Tyler Nance"
    ],
    "link": "https://www.jacobspavilion.com/events/detail?event_id=1366509",
    "date": "2026-09-11T00:00:01",
    "venue": "Jacobs Pavilion at Nautica"
  }
]
